netbox_nornir/__init__.py
netbox_nornir/constraints.py
netbox_nornir/exceptions.py
netbox_nornir/plugins/credentials/__init__.py
netbox_nornir/plugins/credentials/aws_ssm.py
netbox_nornir/plugins/credentials/base.py
netbox_nornir/plugins/credentials/env_vars.py
netbox_nornir/plugins/inventory/netbox_orm.py
netbox_nornir/plugins/tasks/dispatcher/__init__.py
netbox_nornir/plugins/tasks/dispatcher/arista_eos.py
netbox_nornir/plugins/tasks/dispatcher/cisco_aireos.py
netbox_nornir/plugins/tasks/dispatcher/cisco_asa.py
netbox_nornir/plugins/tasks/dispatcher/cisco_ios.py
netbox_nornir/plugins/tasks/dispatcher/cisco_ios_restconf.py
netbox_nornir/plugins/tasks/dispatcher/cisco_ios_xr.py
netbox_nornir/plugins/tasks/dispatcher/cisco_nxos.py
netbox_nornir/plugins/tasks/dispatcher/cisco_wlc.py
netbox_nornir/plugins/tasks/dispatcher/default.py
netbox_nornir/plugins/tasks/dispatcher/fortinet_fortios.py
netbox_nornir/plugins/tasks/dispatcher/juniper_junos.py
netbox_nornir/plugins/tasks/dispatcher/netscaler.py
netbox_nornir/plugins/tasks/dispatcher/paloalto_panos.py
netbox_nornir/utils.py
netbox_nornir-0.1.1b3.dist-info/LICENSE
netbox_nornir-0.1.1b3.dist-info/METADATA
netbox_nornir-0.1.1b3.dist-info/WHEEL
netbox_nornir-0.1.1b3.dist-info/RECORD
