Metadata-Version: 2.1
Name: netbox-nornir
Version: 0.1.1b3
Summary: 
Author: OpticoreIT
Author-email: opensource@opticoreit.com
Requires-Python: >=3.8,<4.0
Classifier: Programming Language :: Python :: 3
Classifier: Programming Language :: Python :: 3.8
Classifier: Programming Language :: Python :: 3.9
Classifier: Programming Language :: Python :: 3.10
Classifier: Programming Language :: Python :: 3.11
Requires-Dist: boto3 (>=1.26.106,<2.0.0)
Requires-Dist: netmiko (>=4.1.2,<5.0.0)
Requires-Dist: netutils (>=1.4.1,<2.0.0)
Requires-Dist: nornir (>=3.3.0,<4.0.0)
Requires-Dist: nornir-napalm (>=0.3.0,<0.4.0)
Requires-Dist: nornir-netmiko (>=0,<1)
